pywe_wxa_sec/__init__.py
pywe_wxa_sec/pywxasec.py
pywe_wxa_sec-1.0.3.dist-info/METADATA
pywe_wxa_sec-1.0.3.dist-info/WHEEL
pywe_wxa_sec-1.0.3.dist-info/top_level.txt
pywe_wxa_sec-1.0.3.dist-info/RECORD
