Metadata-Version: 2.1
Name: pywe-wxa-sec
Version: 1.0.3
Summary: Wechat MiniProgram Security Module for Python.
Home-page: https://github.com/sdkwe/pywe-wxa-sec
Author: Hackathon
Author-email: kimi.huang@brightcells.com
License: UNKNOWN
Keywords: Wechat Weixin MiniProgram Security
Platform: UNKNOWN
Classifier: License :: OSI Approved :: BSD License
Classifier: Programming Language :: Python
Classifier: Programming Language :: Python :: 2
Classifier: Programming Language :: Python :: 2.6
Classifier: Programming Language :: Python :: 2.7
Classifier: Programming Language :: Python :: 3
Classifier: Programming Language :: Python :: 3.2
Classifier: Programming Language :: Python :: 3.3
Classifier: Programming Language :: Python :: 3.4
Classifier: Topic :: Software Development :: Libraries :: Python Modules
Requires-Dist: pywe-base (>=1.0.6)
Requires-Dist: pywe-token (>=1.0.6)
